packagehelp/__init__.py
packagehelp/reqh/__init__.py
packagehelp/reqh/useragents.py
packagehelp-1.0.0.dist-info/LICENSE
packagehelp-1.0.0.dist-info/METADATA
packagehelp-1.0.0.dist-info/WHEEL
packagehelp-1.0.0.dist-info/top_level.txt
packagehelp-1.0.0.dist-info/RECORD
